README.rst
setup.py
python_zanox_api.egg-info/PKG-INFO
python_zanox_api.egg-info/SOURCES.txt
python_zanox_api.egg-info/dependency_links.txt
python_zanox_api.egg-info/top_level.txt
python_zanox_api.egg-info/zip-safe
zanox/__init__.py
zanox/apis.py
zanox/test.py