Metadata-Version: 1.1
Name: python-zanox-api
Version: 0.2.5
Summary: Python Zanox API - https://developer.zanox.com
Home-page: http://github.com/baskoopmans/python-zanox-api
Author: Bas Koopmans
Author-email: email@baskoopmans.nl
License: BSD
Download-URL: http://github.com/baskoopmans/python-zanox-api/downloads
Platform: UNKNOWN
Classifier: Development Status :: 4 - Beta
Classifier: Environment :: Web Environment
Classifier: Intended Audience :: Developers
Classifier: License :: OSI Approved :: BSD License
Classifier: Operating System :: OS Independent
Classifier: Programming Language :: Python
Classifier: Topic :: Software Development :: Libraries :: Python Modules
